good_clickhouse/__init__.py
good_clickhouse/_client.py
good_clickhouse/_types.py
good_clickhouse/chdb.py
good_clickhouse/collection.py
good_clickhouse/query.py
good_clickhouse-0.2.24.dist-info/METADATA
good_clickhouse-0.2.24.dist-info/WHEEL
good_clickhouse-0.2.24.dist-info/RECORD
