Metadata-Version: 2.4
Name: good-clickhouse
Version: 0.2.24
Summary: Clickhouse client for Good Kiwi
Author-email: Chris Goddard <chris@goodkiwi.llc>
Requires-Python: >=3.12
Requires-Dist: aioch>=0.0.2
Requires-Dist: clickhouse-cityhash>=1.0.2.4
Requires-Dist: clickhouse-connect
Requires-Dist: clickhouse-driver>=0.2.9
Requires-Dist: good-common
Requires-Dist: jinja2>=3.1.6
Requires-Dist: lz4==4.3.3
Requires-Dist: pydantic-settings>=2.9.1
Requires-Dist: python-ulid>=3.0.0
Requires-Dist: tenacity>=9.1.2
Provides-Extra: chdb
Requires-Dist: chdb==3.2.0; extra == 'chdb'
